{
  "meta": {
    "type": "db",
    "canSave": false,
    "canEdit": false,
    "canStar": true,
    "slug": "airflow",
    "expires": "0001-01-01T00:00:00Z",
    "created": "2017-12-06T17:45:12Z",
    "updated": "2019-03-06T16:30:21Z",
    "updatedBy": "admin",
    "createdBy": "admin",
    "version": 43
  },
  "dashboard": {
    "annotations": {
      "list": []
    },
    "editable": true,
    "gnetId": null,
    "graphTooltip": 1,
    "hideControls": false,
    "id": 8,
    "links": [],
    "refresh": "5m",
    "rows": [
      {
        "collapse": true,
        "height": 211,
        "panels": [
          {
            "aliasColors": {},
            "bars": false,
            "dashLength": 10,
            "dashes": false,
            "datasource": null,
            "fill": 1,
            "id": 8,
            "legend": {
              "alignAsTable": true,
              "avg": true,
              "current": false,
              "max": false,
              "min": false,
              "rightSide": true,
              "show": true,
              "total": false,
              "values": true
            },
            "lines": true,
            "linewidth": 1,
            "links": [],
            "minSpan": 6,
            "nullPointMode": "null",
            "percentage": false,
            "pointradius": 1,
            "points": true,
            "renderer": "flot",
            "seriesOverrides": [],
            "spaceLength": 10,
            "span": 8,
            "stack": true,
            "steppedLine": false,
            "targets": [
              {
                "hide": false,
                "refId": "B",
                "target": "aliasByNode(sortByMinima($airflow_master_servers.exec.per_ten_min.airflow.database.dag_id.$dag_id.running), 6)",
                "textEditor": false
              }
            ],
            "thresholds": [],
            "timeFrom": null,
            "timeShift": null,
            "title": "DAGs running on $airflow_master_servers cluster(s)",
            "tooltip": {
              "shared": true,
              "sort": 0,
              "value_type": "individual"
            },
            "type": "graph",
            "xaxis": {
              "buckets": null,
              "mode": "time",
              "name": null,
              "show": true,
              "values": []
            },
            "yaxes": [
              {
                "format": "short",
                "label": null,
                "logBase": 1,
                "max": null,
                "min": "0",
                "show": true
              },
              {
                "format": "short",
                "label": null,
                "logBase": 1,
                "max": null,
                "min": null,
                "show": true
              }
            ]
          },
          {
            "aliasColors": {},
            "bars": true,
            "dashLength": 10,
            "dashes": false,
            "datasource": null,
            "fill": 1,
            "id": 28,
            "legend": {
              "alignAsTable": true,
              "avg": true,
              "current": false,
              "max": false,
              "min": false,
              "rightSide": true,
              "show": false,
              "total": false,
              "values": true
            },
            "lines": false,
            "linewidth": 1,
            "links": [],
            "minSpan": 6,
            "nullPointMode": "null",
            "percentage": false,
            "pointradius": 1,
            "points": false,
            "renderer": "flot",
            "seriesOverrides": [],
            "spaceLength": 10,
            "span": 4,
            "stack": false,
            "steppedLine": false,
            "targets": [
              {
                "hide": false,
                "refId": "B",
                "target": "aliasByMetric(sumSeriesWithWildcards(perSecond($airflow_master_servers.exec.per_ten_min.airflow.database.dag_id.$dag_id.*), 6))",
                "textEditor": false
              }
            ],
            "thresholds": [],
            "timeFrom": null,
            "timeShift": null,
            "title": "Integrated DAGs results/s on $airflow_master_servers",
            "tooltip": {
              "shared": false,
              "sort": 0,
              "value_type": "individual"
            },
            "type": "graph",
            "xaxis": {
              "buckets": null,
              "mode": "series",
              "name": null,
              "show": true,
              "values": [
                "total"
              ]
            },
            "yaxes": [
              {
                "format": "short",
                "label": null,
                "logBase": 1,
                "max": null,
                "min": "0",
                "show": true
              },
              {
                "format": "short",
                "label": null,
                "logBase": 1,
                "max": null,
                "min": null,
                "show": true
              }
            ]
          }
        ],
        "repeat": null,
        "repeatIteration": null,
        "repeatRowId": null,
        "showTitle": false,
        "title": "Dashboard Row",
        "titleSize": "h6"
      },
      {
        "collapse": false,
        "height": 250,
        "panels": [
          {
            "aliasColors": {},
            "bars": false,
            "dashLength": 10,
            "dashes": false,
            "datasource": null,
            "fill": 1,
            "id": 21,
            "legend": {
              "alignAsTable": true,
              "avg": true,
              "current": false,
              "max": false,
              "min": false,
              "rightSide": true,
              "show": true,
              "sort": "avg",
              "sortDesc": true,
              "total": false,
              "values": true
            },
            "lines": true,
            "linewidth": 1,
            "links": [],
            "minSpan": 6,
            "nullPointMode": "null",
            "percentage": false,
            "pointradius": 1,
            "points": true,
            "renderer": "flot",
            "seriesOverrides": [],
            "spaceLength": 10,
            "span": 3,
            "stack": true,
            "steppedLine": false,
            "targets": [
              {
                "hide": false,
                "refId": "B",
                "target": "aliasByNode(sortByMinima($worker_servers.exec.per_ten_min.airflow.database.jobs.running), 0)",
                "textEditor": false
              }
            ],
            "thresholds": [],
            "timeFrom": null,
            "timeShift": null,
            "title": "jobs \"running\"",
            "tooltip": {
              "shared": true,
              "sort": 0,
              "value_type": "individual"
            },
            "type": "graph",
            "xaxis": {
              "buckets": null,
              "mode": "time",
              "name": null,
              "show": true,
              "values": []
            },
            "yaxes": [
              {
                "format": "short",
                "label": null,
                "logBase": 1,
                "max": null,
                "min": "0",
                "show": true
              },
              {
                "format": "short",
                "label": null,
                "logBase": 1,
                "max": null,
                "min": null,
                "show": true
              }
            ]
          },
          {
            "aliasColors": {},
            "bars": false,
            "dashLength": 10,
            "dashes": false,
            "datasource": null,
            "fill": 1,
            "id": 50,
            "legend": {
              "alignAsTable": true,
              "avg": true,
              "current": false,
              "max": false,
              "min": false,
              "rightSide": true,
              "show": true,
              "sort": "avg",
              "sortDesc": true,
              "total": false,
              "values": true
            },
            "lines": true,
            "linewidth": 1,
            "links": [],
            "minSpan": 6,
            "nullPointMode": "null",
            "percentage": false,
            "pointradius": 1,
            "points": true,
            "renderer": "flot",
            "seriesOverrides": [],
            "spaceLength": 10,
            "span": 9,
            "stack": false,
            "steppedLine": false,
            "targets": [
              {
                "hide": false,
                "refId": "B",
                "target": "aliasByNode(sortByMinima(movingAverage(perSecond($worker_servers.exec.per_ten_min.airflow.database.jobs.failed), 3)), 0)",
                "textEditor": false
              }
            ],
            "thresholds": [],
            "timeFrom": null,
            "timeShift": null,
            "title": "jobs \"failed\" / s (MA 3)",
            "tooltip": {
              "shared": true,
              "sort": 0,
              "value_type": "individual"
            },
            "type": "graph",
            "xaxis": {
              "buckets": null,
              "mode": "time",
              "name": null,
              "show": true,
              "values": []
            },
            "yaxes": [
              {
                "format": "short",
                "label": null,
                "logBase": 1,
                "max": null,
                "min": "0",
                "show": true
              },
              {
                "format": "short",
                "label": null,
                "logBase": 1,
                "max": null,
                "min": null,
                "show": true
              }
            ]
          },
          {
            "aliasColors": {},
            "bars": false,
            "dashLength": 10,
            "dashes": false,
            "datasource": null,
            "fill": 1,
            "id": 22,
            "legend": {
              "alignAsTable": true,
              "avg": true,
              "current": false,
              "max": false,
              "min": false,
              "rightSide": true,
              "show": true,
              "sort": "avg",
              "sortDesc": true,
              "total": false,
              "values": true
            },
            "lines": true,
            "linewidth": 1,
            "links": [],
            "minSpan": 6,
            "nullPointMode": "null",
            "percentage": false,
            "pointradius": 1,
            "points": true,
            "renderer": "flot",
            "seriesOverrides": [],
            "spaceLength": 10,
            "span": 3,
            "stack": true,
            "steppedLine": false,
            "targets": [
              {
                "hide": false,
                "refId": "B",
                "target": "aliasByNode(sortByMinima(sumSeriesWithWildcards($worker_servers.exec.per_ten_min.airflow.database.jobs.*, 0)), 5)",
                "textEditor": false
              }
            ],
            "thresholds": [],
            "timeFrom": null,
            "timeShift": null,
            "title": "jobs status",
            "tooltip": {
              "shared": true,
              "sort": 0,
              "value_type": "individual"
            },
            "type": "graph",
            "xaxis": {
              "buckets": null,
              "mode": "time",
              "name": null,
              "show": true,
              "values": []
            },
            "yaxes": [
              {
                "format": "short",
                "label": null,
                "logBase": 10,
                "max": null,
                "min": "0",
                "show": true
              },
              {
                "format": "short",
                "label": null,
                "logBase": 1,
                "max": null,
                "min": null,
                "show": true
              }
            ]
          },
          {
            "aliasColors": {},
            "bars": false,
            "dashLength": 10,
            "dashes": false,
            "datasource": null,
            "fill": 1,
            "id": 23,
            "legend": {
              "alignAsTable": true,
              "avg": true,
              "current": false,
              "max": false,
              "min": false,
              "rightSide": true,
              "show": true,
              "sort": "avg",
              "sortDesc": true,
              "total": false,
              "values": true
            },
            "lines": true,
            "linewidth": 1,
            "links": [],
            "minSpan": 6,
            "nullPointMode": "null",
            "percentage": false,
            "pointradius": 1,
            "points": true,
            "renderer": "flot",
            "seriesOverrides": [],
            "spaceLength": 10,
            "span": 9,
            "stack": false,
            "steppedLine": false,
            "targets": [
              {
                "hide": false,
                "refId": "B",
                "target": "aliasByNode(sortByMinima(movingAverage(perSecond($worker_servers.exec.per_ten_min.airflow.database.jobs.success), 3)), 0)",
                "textEditor": false
              }
            ],
            "thresholds": [],
            "timeFrom": null,
            "timeShift": null,
            "title": "jobs \"success\" / s (MA 3)",
            "tooltip": {
              "shared": true,
              "sort": 0,
              "value_type": "individual"
            },
            "type": "graph",
            "xaxis": {
              "buckets": null,
              "mode": "time",
              "name": null,
              "show": true,
              "values": []
            },
            "yaxes": [
              {
                "format": "short",
                "label": null,
                "logBase": 1,
                "max": null,
                "min": "0",
                "show": true
              },
              {
                "format": "short",
                "label": null,
                "logBase": 1,
                "max": null,
                "min": null,
                "show": true
              }
            ]
          }
        ],
        "repeat": null,
        "repeatIteration": null,
        "repeatRowId": null,
        "showTitle": false,
        "title": "Dashboard Row",
        "titleSize": "h6"
      },
      {
        "collapse": false,
        "height": 339,
        "panels": [
          {
            "aliasColors": {},
            "bars": false,
            "dashLength": 10,
            "dashes": false,
            "datasource": null,
            "fill": 8,
            "id": 13,
            "legend": {
              "alignAsTable": true,
              "avg": false,
              "current": true,
              "hideEmpty": true,
              "hideZero": true,
              "max": false,
              "min": false,
              "rightSide": true,
              "show": true,
              "sort": null,
              "sortDesc": null,
              "total": false,
              "values": true
            },
            "lines": true,
            "linewidth": 0,
            "links": [],
            "nullPointMode": "null",
            "percentage": false,
            "pointradius": 1,
            "points": false,
            "renderer": "flot",
            "seriesOverrides": [],
            "spaceLength": 10,
            "span": 3,
            "stack": true,
            "steppedLine": false,
            "targets": [
              {
                "refId": "A",
                "target": "aliasByMetric(sortByMaxima($product_servers.exec.per_ten_min.product_metadata.products.*))"
              }
            ],
            "thresholds": [],
            "timeFrom": null,
            "timeShift": null,
            "title": "product counts by type from $product_servers",
            "tooltip": {
              "shared": false,
              "sort": 0,
              "value_type": "individual"
            },
            "type": "graph",
            "xaxis": {
              "buckets": null,
              "mode": "time",
              "name": null,
              "show": true,
              "values": []
            },
            "yaxes": [
              {
                "format": "short",
                "label": null,
                "logBase": 1,
                "max": null,
                "min": "0",
                "show": true
              },
              {
                "format": "short",
                "label": null,
                "logBase": 1,
                "max": null,
                "min": null,
                "show": false
              }
            ]
          },
          {
            "aliasColors": {},
            "bars": false,
            "dashLength": 10,
            "dashes": false,
            "datasource": null,
            "fill": 2,
            "id": 44,
            "legend": {
              "alignAsTable": true,
              "avg": true,
              "current": true,
              "hideEmpty": true,
              "hideZero": true,
              "max": false,
              "min": false,
              "rightSide": true,
              "show": true,
              "sort": "avg",
              "sortDesc": true,
              "total": false,
              "values": true
            },
            "lines": true,
            "linewidth": 1,
            "links": [],
            "nullPointMode": "null",
            "percentage": false,
            "pointradius": 1,
            "points": true,
            "renderer": "flot",
            "seriesOverrides": [],
            "spaceLength": 10,
            "span": 9,
            "stack": false,
            "steppedLine": false,
            "targets": [
              {
                "refId": "A",
                "target": "aliasByMetric(perSecond(sortByMaxima($product_servers.exec.per_ten_min.product_metadata.products.*)))"
              }
            ],
            "thresholds": [],
            "timeFrom": null,
            "timeShift": null,
            "title": "Δ type",
            "tooltip": {
              "shared": false,
              "sort": 0,
              "value_type": "individual"
            },
            "type": "graph",
            "xaxis": {
              "buckets": null,
              "mode": "time",
              "name": null,
              "show": true,
              "values": []
            },
            "yaxes": [
              {
                "format": "short",
                "label": "",
                "logBase": 1,
                "max": null,
                "min": null,
                "show": true
              },
              {
                "format": "short",
                "label": null,
                "logBase": 1,
                "max": null,
                "min": null,
                "show": true
              }
            ]
          },
          {
            "aliasColors": {},
            "bars": false,
            "dashLength": 10,
            "dashes": false,
            "datasource": null,
            "fill": 5,
            "id": 16,
            "legend": {
              "alignAsTable": true,
              "avg": false,
              "current": true,
              "hideEmpty": true,
              "hideZero": true,
              "max": false,
              "min": false,
              "rightSide": true,
              "show": true,
              "total": false,
              "values": true
            },
            "lines": true,
            "linewidth": 1,
            "links": [],
            "nullPointMode": "null",
            "percentage": false,
            "pointradius": 1,
            "points": true,
            "renderer": "flot",
            "seriesOverrides": [],
            "spaceLength": 10,
            "span": 3,
            "stack": true,
            "steppedLine": false,
            "targets": [
              {
                "refId": "A",
                "target": "aliasByMetric(sortByMinima($product_servers.exec.per_ten_min.product_metadata.status.*))",
                "textEditor": false
              }
            ],
            "thresholds": [],
            "timeFrom": null,
            "timeShift": null,
            "title": "product counts by status from $product_servers",
            "tooltip": {
              "shared": true,
              "sort": 0,
              "value_type": "individual"
            },
            "type": "graph",
            "xaxis": {
              "buckets": null,
              "mode": "time",
              "name": null,
              "show": true,
              "values": []
            },
            "yaxes": [
              {
                "format": "short",
                "label": "",
                "logBase": 1,
                "max": null,
                "min": null,
                "show": true
              },
              {
                "format": "short",
                "label": null,
                "logBase": 1,
                "max": null,
                "min": null,
                "show": false
              }
            ]
          },
          {
            "aliasColors": {},
            "bars": false,
            "dashLength": 10,
            "dashes": false,
            "datasource": null,
            "fill": 2,
            "id": 45,
            "legend": {
              "alignAsTable": true,
              "avg": true,
              "current": true,
              "hideEmpty": true,
              "hideZero": true,
              "max": false,
              "min": false,
              "rightSide": true,
              "show": true,
              "total": false,
              "values": true
            },
            "lines": true,
            "linewidth": 1,
            "links": [],
            "nullPointMode": "null",
            "percentage": false,
            "pointradius": 1,
            "points": true,
            "renderer": "flot",
            "seriesOverrides": [],
            "spaceLength": 10,
            "span": 9,
            "stack": false,
            "steppedLine": false,
            "targets": [
              {
                "refId": "A",
                "target": "aliasByMetric(perSecond(sortByMinima($product_servers.exec.per_ten_min.product_metadata.status.*)))",
                "textEditor": false
              }
            ],
            "thresholds": [],
            "timeFrom": null,
            "timeShift": null,
            "title": "Δ status",
            "tooltip": {
              "shared": true,
              "sort": 0,
              "value_type": "individual"
            },
            "type": "graph",
            "xaxis": {
              "buckets": null,
              "mode": "time",
              "name": null,
              "show": true,
              "values": []
            },
            "yaxes": [
              {
                "format": "short",
                "label": "",
                "logBase": 1,
                "max": null,
                "min": null,
                "show": true
              },
              {
                "format": "short",
                "label": null,
                "logBase": 1,
                "max": null,
                "min": null,
                "show": true
              }
            ]
          }
        ],
        "repeat": null,
        "repeatIteration": null,
        "repeatRowId": null,
        "showTitle": false,
        "title": "Dashboard Row",
        "titleSize": "h6"
      },
      {
        "collapse": false,
        "height": 151,
        "panels": [
          {
            "cacheTimeout": null,
            "colorBackground": true,
            "colorValue": false,
            "colors": [
              "rgba(29, 29, 29, 0.9)",
              "rgba(161, 216, 150, 0.89)",
              "rgba(50, 172, 45, 0.97)"
            ],
            "datasource": null,
            "format": "none",
            "gauge": {
              "maxValue": 100,
              "minValue": 0,
              "show": false,
              "thresholdLabels": false,
              "thresholdMarkers": true
            },
            "id": 30,
            "interval": null,
            "links": [],
            "mappingType": 1,
            "mappingTypes": [
              {
                "name": "value to text",
                "value": 1
              },
              {
                "name": "range to text",
                "value": 2
              }
            ],
            "maxDataPoints": 100,
            "nullPointMode": "connected",
            "nullText": null,
            "postfix": "",
            "postfixFontSize": "50%",
            "prefix": "",
            "prefixFontSize": "50%",
            "rangeMaps": [
              {
                "from": "null",
                "text": "N/A",
                "to": "null"
              }
            ],
            "scopedVars": {
              "dag_id": {
                "selected": true,
                "text": "file_watcher",
                "value": "file_watcher"
              }
            },
            "span": 1,
            "sparkline": {
              "fillColor": "rgba(31, 118, 189, 0.18)",
              "full": true,
              "lineColor": "rgb(31, 120, 193)",
              "show": true
            },
            "tableColumn": "",
            "targets": [
              {
                "refId": "A",
                "target": "$airflow_master_servers.exec.per_ten_min.airflow.database.dag_id.$dag_id.running"
              }
            ],
            "thresholds": "1,10",
            "title": "# running",
            "type": "singlestat",
            "valueFontSize": "80%",
            "valueMaps": [
              {
                "op": "=",
                "text": "N/A",
                "value": "null"
              }
            ],
            "valueName": "current"
          },
          {
            "aliasColors": {},
            "bars": true,
            "dashLength": 10,
            "dashes": false,
            "datasource": null,
            "fill": 1,
            "id": 5,
            "legend": {
              "alignAsTable": true,
              "avg": true,
              "current": false,
              "max": false,
              "min": false,
              "rightSide": true,
              "show": true,
              "total": false,
              "values": true
            },
            "lines": false,
            "linewidth": 1,
            "links": [
              {
                "dashUri": "db/airflow-dag-drilldown",
                "dashboard": "airflow-dag-drilldown",
                "includeVars": true,
                "keepTime": true,
                "targetBlank": true,
                "title": "airflow-dag-drilldown",
                "type": "dashboard"
              }
            ],
            "minSpan": 6,
            "nullPointMode": "null",
            "percentage": false,
            "pointradius": 1,
            "points": false,
            "renderer": "flot",
            "repeat": null,
            "scopedVars": {
              "dag_id": {
                "selected": true,
                "text": "file_watcher",
                "value": "file_watcher"
              }
            },
            "seriesOverrides": [],
            "spaceLength": 10,
            "span": 5,
            "stack": true,
            "steppedLine": false,
            "targets": [
              {
                "hide": false,
                "refId": "B",
                "target": "aliasByNode(perSecond($airflow_master_servers.exec.per_ten_min.airflow.database.dag_id.$dag_id.{success,failed}), 7)",
                "textEditor": false
              }
            ],
            "thresholds": [],
            "timeFrom": null,
            "timeShift": null,
            "title": "{fail or success} / s",
            "tooltip": {
              "shared": true,
              "sort": 0,
              "value_type": "individual"
            },
            "type": "graph",
            "xaxis": {
              "buckets": null,
              "mode": "time",
              "name": null,
              "show": true,
              "values": []
            },
            "yaxes": [
              {
                "format": "short",
                "label": "",
                "logBase": 1,
                "max": null,
                "min": "0",
                "show": true
              },
              {
                "format": "short",
                "label": null,
                "logBase": 1,
                "max": null,
                "min": null,
                "show": true
              }
            ]
          },
          {
            "aliasColors": {},
            "bars": true,
            "dashLength": 10,
            "dashes": false,
            "datasource": null,
            "fill": 1,
            "id": 29,
            "legend": {
              "avg": false,
              "current": false,
              "max": false,
              "min": false,
              "show": false,
              "total": false,
              "values": false
            },
            "lines": false,
            "linewidth": 1,
            "links": [],
            "nullPointMode": "null",
            "percentage": false,
            "pointradius": 5,
            "points": false,
            "renderer": "flot",
            "repeat": null,
            "scopedVars": {
              "dag_id": {
                "selected": true,
                "text": "file_watcher",
                "value": "file_watcher"
              }
            },
            "seriesOverrides": [],
            "spaceLength": 10,
            "span": 4,
            "stack": true,
            "steppedLine": false,
            "targets": [
              {
                "refId": "A",
                "target": "aliasByMetric($airflow_master_servers.exec.per_ten_min.airflow.database.dag_id.$dag_id.{failed,success})"
              }
            ],
            "thresholds": [],
            "timeFrom": null,
            "timeShift": null,
            "title": "total fails & successes",
            "tooltip": {
              "shared": true,
              "sort": 0,
              "value_type": "individual"
            },
            "type": "graph",
            "xaxis": {
              "buckets": null,
              "mode": "time",
              "name": null,
              "show": true,
              "values": [
                "current"
              ]
            },
            "yaxes": [
              {
                "format": "short",
                "label": "",
                "logBase": 1,
                "max": null,
                "min": "0",
                "show": true
              },
              {
                "format": "short",
                "label": null,
                "logBase": 1,
                "max": null,
                "min": null,
                "show": true
              }
            ]
          },
          {
            "aliasColors": {},
            "bars": true,
            "dashLength": 10,
            "dashes": false,
            "datasource": null,
            "fill": 1,
            "id": 31,
            "legend": {
              "alignAsTable": false,
              "avg": false,
              "current": false,
              "hideEmpty": false,
              "hideZero": false,
              "max": true,
              "min": false,
              "rightSide": false,
              "show": false,
              "total": false,
              "values": true
            },
            "lines": false,
            "linewidth": 1,
            "links": [],
            "nullPointMode": "null",
            "percentage": false,
            "pointradius": 5,
            "points": false,
            "renderer": "flot",
            "scopedVars": {
              "dag_id": {
                "selected": true,
                "text": "file_watcher",
                "value": "file_watcher"
              }
            },
            "seriesOverrides": [],
            "spaceLength": 10,
            "span": 2,
            "stack": false,
            "steppedLine": false,
            "targets": [
              {
                "refId": "A",
                "target": "aliasByMetric(perSecond($airflow_master_servers.exec.per_ten_min.airflow.database.dag_id.$dag_id.{failed,success}))"
              }
            ],
            "thresholds": [],
            "timeFrom": null,
            "timeShift": null,
            "title": "fail/success rate (avg per second)",
            "tooltip": {
              "shared": false,
              "sort": 0,
              "value_type": "individual"
            },
            "type": "graph",
            "xaxis": {
              "buckets": null,
              "mode": "series",
              "name": null,
              "show": true,
              "values": [
                "avg"
              ]
            },
            "yaxes": [
              {
                "format": "short",
                "label": "",
                "logBase": 1,
                "max": null,
                "min": "0",
                "show": true
              },
              {
                "format": "short",
                "label": null,
                "logBase": 1,
                "max": null,
                "min": null,
                "show": true
              }
            ]
          }
        ],
        "repeat": "dag_id",
        "repeatIteration": null,
        "repeatRowId": null,
        "showTitle": true,
        "title": "$dag_id",
        "titleSize": "h6"
      },
      {
        "collapse": true,
        "height": 250,
        "panels": [
          {
            "aliasColors": {},
            "bars": false,
            "dashLength": 10,
            "dashes": false,
            "datasource": null,
            "fill": 1,
            "id": 2,
            "legend": {
              "avg": false,
              "current": false,
              "max": false,
              "min": false,
              "show": false,
              "total": false,
              "values": false
            },
            "lines": true,
            "linewidth": 1,
            "links": [],
            "nullPointMode": "null",
            "percentage": false,
            "pointradius": 5,
            "points": false,
            "renderer": "flot",
            "seriesOverrides": [],
            "spaceLength": 10,
            "span": 4,
            "stack": false,
            "steppedLine": false,
            "targets": [
              {
                "refId": "A",
                "target": "$airflow_master_servers.exec.airflow.dag_run"
              }
            ],
            "thresholds": [],
            "timeFrom": null,
            "timeShift": null,
            "title": "DAG Runs",
            "tooltip": {
              "shared": true,
              "sort": 0,
              "value_type": "individual"
            },
            "type": "graph",
            "xaxis": {
              "buckets": null,
              "mode": "time",
              "name": null,
              "show": true,
              "values": []
            },
            "yaxes": [
              {
                "format": "short",
                "label": null,
                "logBase": 1,
                "max": null,
                "min": null,
                "show": true
              },
              {
                "format": "short",
                "label": null,
                "logBase": 1,
                "max": null,
                "min": null,
                "show": true
              }
            ]
          },
          {
            "aliasColors": {},
            "bars": false,
            "dashLength": 10,
            "dashes": false,
            "datasource": null,
            "fill": 1,
            "id": 4,
            "legend": {
              "avg": false,
              "current": false,
              "max": false,
              "min": false,
              "show": false,
              "total": false,
              "values": false
            },
            "lines": true,
            "linewidth": 1,
            "links": [],
            "nullPointMode": "null",
            "percentage": false,
            "pointradius": 5,
            "points": false,
            "renderer": "flot",
            "seriesOverrides": [],
            "spaceLength": 10,
            "span": 4,
            "stack": false,
            "steppedLine": false,
            "targets": [
              {
                "refId": "A",
                "target": "$airflow_master_servers.exec.airflow.task_instance"
              }
            ],
            "thresholds": [],
            "timeFrom": null,
            "timeShift": null,
            "title": "Task Instances",
            "tooltip": {
              "shared": true,
              "sort": 0,
              "value_type": "individual"
            },
            "type": "graph",
            "xaxis": {
              "buckets": null,
              "mode": "time",
              "name": null,
              "show": true,
              "values": []
            },
            "yaxes": [
              {
                "format": "short",
                "label": null,
                "logBase": 1,
                "max": null,
                "min": null,
                "show": true
              },
              {
                "format": "short",
                "label": null,
                "logBase": 1,
                "max": null,
                "min": null,
                "show": true
              }
            ]
          },
          {
            "aliasColors": {},
            "bars": false,
            "dashLength": 10,
            "dashes": false,
            "datasource": null,
            "fill": 1,
            "id": 3,
            "legend": {
              "avg": false,
              "current": false,
              "max": false,
              "min": false,
              "show": false,
              "total": false,
              "values": false
            },
            "lines": true,
            "linewidth": 1,
            "links": [],
            "nullPointMode": "null",
            "percentage": false,
            "pointradius": 5,
            "points": false,
            "renderer": "flot",
            "seriesOverrides": [],
            "spaceLength": 10,
            "span": 4,
            "stack": false,
            "steppedLine": false,
            "targets": [
              {
                "refId": "A",
                "target": "$airflow_master_servers.exec.airflow.job"
              }
            ],
            "thresholds": [],
            "timeFrom": null,
            "timeShift": null,
            "title": "Jobs",
            "tooltip": {
              "shared": true,
              "sort": 0,
              "value_type": "individual"
            },
            "type": "graph",
            "xaxis": {
              "buckets": null,
              "mode": "time",
              "name": null,
              "show": true,
              "values": []
            },
            "yaxes": [
              {
                "format": "short",
                "label": null,
                "logBase": 1,
                "max": null,
                "min": null,
                "show": true
              },
              {
                "format": "short",
                "label": null,
                "logBase": 1,
                "max": null,
                "min": null,
                "show": true
              }
            ]
          }
        ],
        "repeat": null,
        "repeatIteration": null,
        "repeatRowId": null,
        "showTitle": false,
        "title": "old (defunct) metrics",
        "titleSize": "h6"
      }
    ],
    "schemaVersion": 14,
    "style": "dark",
    "tags": [
      "sysadmin"
    ],
    "templating": {
      "list": [
        {
          "allValue": null,
          "current": {
            "text": "imars-airflow01",
            "value": [
              "imars-airflow01"
            ]
          },
          "datasource": "IMaRS graphite server",
          "hide": 0,
          "includeAll": false,
          "label": null,
          "multi": true,
          "name": "airflow_master_servers",
          "options": [],
          "query": "imars-airflow*",
          "refresh": 2,
          "regex": "",
          "sort": 1,
          "tagValuesQuery": "",
          "tags": [],
          "tagsQuery": "",
          "type": "query",
          "useTags": false
        },
        {
          "allValue": null,
          "current": {
            "text": "file_watcher",
            "value": [
              "file_watcher"
            ]
          },
          "datasource": "IMaRS graphite server",
          "hide": 0,
          "includeAll": true,
          "label": null,
          "multi": true,
          "name": "dag_id",
          "options": [],
          "query": "$airflow_master_servers.exec.per_ten_min.airflow.database.dag_id.*",
          "refresh": 2,
          "regex": "",
          "sort": 0,
          "tagValuesQuery": "",
          "tags": [],
          "tagsQuery": "",
          "type": "query",
          "useTags": false
        },
        {
          "allValue": null,
          "current": {
            "text": "imars-sql-hydra",
            "value": "imars-sql-hydra"
          },
          "datasource": "IMaRS graphite server",
          "hide": 0,
          "includeAll": false,
          "label": null,
          "multi": true,
          "name": "product_servers",
          "options": [],
          "query": "*",
          "refresh": 2,
          "regex": "",
          "sort": 0,
          "tagValuesQuery": "",
          "tags": [],
          "tagsQuery": "",
          "type": "query",
          "useTags": false
        },
        {
          "allValue": null,
          "current": {
            "tags": [],
            "text": "imars-airflow-21 + imars-airflow11 + imars-airflow12 + imars-airflow13 + imars-airflow14 + imars-airflow15 + imars-airflow16",
            "value": [
              "imars-airflow-21",
              "imars-airflow11",
              "imars-airflow12",
              "imars-airflow13",
              "imars-airflow14",
              "imars-airflow15",
              "imars-airflow16"
            ]
          },
          "datasource": "IMaRS graphite server",
          "hide": 0,
          "includeAll": false,
          "label": null,
          "multi": true,
          "name": "worker_servers",
          "options": [],
          "query": "imars-airflow*",
          "refresh": 1,
          "regex": "",
          "sort": 1,
          "tagValuesQuery": "",
          "tags": [],
          "tagsQuery": "",
          "type": "query",
          "useTags": false
        }
      ]
    },
    "time": {
      "from": "now-2d",
      "to": "now"
    },
    "timepicker": {
      "refresh_intervals": [
        "5s",
        "10s",
        "30s",
        "1m",
        "5m",
        "15m",
        "30m",
        "1h",
        "2h",
        "1d"
      ],
      "time_options": [
        "5m",
        "15m",
        "1h",
        "6h",
        "12h",
        "24h",
        "2d",
        "7d",
        "30d"
      ]
    },
    "timezone": "",
    "title": "airflow",
    "version": 43
  }
}
